huycnv/__init__.py
huycnv/plugin.py
huycnv-0.1.0.dist-info/licenses/LICENSE
huycnv-0.1.0.dist-info/METADATA
huycnv-0.1.0.dist-info/WHEEL
huycnv-0.1.0.dist-info/top_level.txt
huycnv-0.1.0.dist-info/RECORD
