Metadata-Version: 2.4
Name: huycnv
Version: 0.1.0
Summary: CNV plugin interface definitions for PGT workflows
Author: CNV-PGT Team
License: MIT License
Project-URL: Homepage, https://example.com/huycnv
Project-URL: Repository, https://example.com/huycnv.git
Classifier: License :: OSI Approved :: MIT License
Classifier: Programming Language :: Python
Classifier: Programming Language :: Python :: 3
Classifier: Programming Language :: Python :: 3.9
Requires-Python: >=3.9
License-File: LICENSE
Requires-Dist: pydantic>=1.10
Dynamic: license-file
